datacompose/__init__.py
datacompose/cli/__init__.py
datacompose/cli/colors.py
datacompose/cli/config.py
datacompose/cli/main.py
datacompose/cli/validation.py
datacompose/cli/commands/__init__.py
datacompose/cli/commands/add.py
datacompose/cli/commands/init.py
datacompose/cli/commands/list.py
datacompose/generators/__init__.py
datacompose/generators/base.py
datacompose/generators/pyspark/__init__.py
datacompose/generators/pyspark/generator.py
datacompose/operators/__init__.py
datacompose/operators/primitives.py
datacompose/transformers/__init__.py
datacompose/transformers/discovery.py
datacompose/transformers/text/__init__.py
datacompose/transformers/text/addresses/__init__.py
datacompose/transformers/text/addresses/pyspark/pyspark_primitives.py
datacompose/transformers/text/datetimes/pyspark/pyspark_primitives.py
datacompose/transformers/text/emails/__init__.py
datacompose/transformers/text/emails/pyspark/pyspark_primitives.py
datacompose/transformers/text/phone_numbers/__init__.py
datacompose/transformers/text/phone_numbers/pyspark/pyspark_primitives.py
datacompose/transformers/text/text/__init__.py
datacompose/transformers/text/text/pyspark/__init__.py
datacompose/transformers/text/text/pyspark/pyspark_primitives.py
datacompose-0.3.0.dist-info/licenses/LICENSE
datacompose-0.3.0.dist-info/METADATA
datacompose-0.3.0.dist-info/WHEEL
datacompose-0.3.0.dist-info/entry_points.txt
datacompose-0.3.0.dist-info/top_level.txt
datacompose-0.3.0.dist-info/RECORD
