Metadata-Version: 2.4
Name: datacompose
Version: 0.3.0
Summary: Copy-pasteable data transformation primitives for PySpark. Inspired by shadcn-svelte.
Author: Datacompose Contributors
Maintainer: Datacompose Contributors
License: MIT
Project-URL: Homepage, https://github.com/tc-cole/datacompose
Project-URL: Documentation, https://github.com/tc-cole/datacompose/tree/main/docs
Project-URL: Repository, https://github.com/tc-cole/datacompose.git
Project-URL: Issues, https://github.com/tc-cole/datacompose/issues
Project-URL: Changelog, https://github.com/tc-cole/datacompose/blob/main/CHANGELOG.md
Keywords: data-cleaning,data-quality,udf,spark,postgres,code-generation,data-pipeline,etl
Classifier: Development Status :: 4 - Beta
Classifier: Intended Audience :: Developers
Classifier: Topic :: Software Development :: Code Generators
Classifier: Topic :: Database
Classifier: Topic :: Software Development :: Libraries :: Python Modules
Classifier: License :: OSI Approved :: MIT License
Classifier: Programming Language :: Python :: 3
Classifier: Programming Language :: Python :: 3.8
Classifier: Programming Language :: Python :: 3.9
Classifier: Programming Language :: Python :: 3.10
Classifier: Programming Language :: Python :: 3.11
Classifier: Programming Language :: Python :: 3.12
Classifier: Operating System :: OS Independent
Requires-Python: >=3.8
License-File: LICENSE
Requires-Dist: jinja2>=3.0.0
Requires-Dist: pyyaml>=6.0
Requires-Dist: click>=8.0.0
Provides-Extra: dev
Requires-Dist: pytest>=7.0.0; extra == "dev"
Requires-Dist: black>=23.0.0; extra == "dev"
Requires-Dist: mypy>=1.0.0; extra == "dev"
Requires-Dist: ruff>=0.1.0; extra == "dev"
Provides-Extra: docs
Requires-Dist: mkdocs>=1.5.3; extra == "docs"
Requires-Dist: mkdocs-material>=9.5.0; extra == "docs"
Requires-Dist: mkdocs-material-extensions>=1.3; extra == "docs"
Requires-Dist: mkdocs-minify-plugin>=0.7.1; extra == "docs"
Requires-Dist: mkdocs-redirects>=1.2.1; extra == "docs"
Requires-Dist: mike>=2.0.0; extra == "docs"
Requires-Dist: pymdown-extensions>=10.5; extra == "docs"
Requires-Dist: pygments>=2.17.0; extra == "docs"
Requires-Dist: mkdocs-git-revision-date-localized-plugin>=1.2.2; extra == "docs"
Requires-Dist: mkdocs-glightbox>=0.3.5; extra == "docs"
Dynamic: license-file
